{
  "learning_objectives": [
    "강화 학습이 무엇인지 정의할 수 있다.",
    "강화 학습에서 에이전트, 환경, 상태, 행동, 보상의 역할을 설명할 수 있다.",
    "강화학습의 목표인 정책(policy)을 최적화하는 과정을 설명할 수 있다."
  ],
  "quizzes": [
    {
      "id": 1,
      "objective_id": 1,
      "question": "강화 학습의 정의에 가장 부합하는 설명은 무엇인가요?",
      "options": {
        "A": "에이전트가 환경과의 상호작용을 통해 정답을 학습하는 과정",
        "B": "에이전트가 환경과 상호작용하며 보상을 최대화하는 방법을 학습하는 과정",
        "C": "에이전트가 최소의 데이터로 최대의 정보를 추출하는 과정",
        "D": "에이전트가 레이블 없는 데이터로부터 패턴을 학습하는 과정"
      },
      "answer": "B",
      "explanation": "강화 학습은 에이전트가 환경과 상호작용하며 보상을 최대화하는 방법을 학습하는 과정입니다."
    },
    {
      "id": 2,
      "objective_id": 1,
      "question": "강화 학습의 정의와 관련하여, 다음 중 틀린 설명은 무엇입니까?",
      "options": {
        "A": "강화 학습은 에이전트가 환경과 상호 작용하며 학습하는 과정이다.",
        "B": "강화 학습은 지도 학습과 같이 정답이 주어지는 상황에서 사용된다.",
        "C": "강화 학습은 에이전트가 시행착오를 통해 학습한다.",
        "D": "강화 학습은 에이전트가 누적 보상을 최대화하는 방향으로 행동을 결정한다."
      },
      "answer": "B",
      "explanation": "강화 학습은 지도학습과 같이 정답이 주어지는 상황에서 사용되지 않습니다. 에이전트는 시행착오를 통해 최적의 행동을 학습합니다."
    },
    {
      "id": 3,
      "objective_id": 1,
      "question": "강화 학습에서, 에이전트가 취하는 행동 후에 받는 즉각적인 피드백을 무엇이라고 하나요?",
      "options": {
        "A": "패널티",
        "B": "그라디언트",
        "C": "보상",
        "D": "오류 신호"
      },
      "answer": "C",
      "explanation": "강화 학습에서 에이전트가 행동을 취한 후 받는 즉각적인 피드백은 보상입니다."
    },
    {
      "id": 4,
      "objective_id": 2,
      "question": "강화 학습에서 '환경'이란 무엇인가요?",
      "options": {
        "A": "에이전트가 취하는 모든 행동",
        "B": "에이전트가 학습을 통해 최적화하는 정책",
        "C": "학습 알고리즘",
        "D": "에이전트에게 주어지는 보상과 새로운 상태"
      },
      "answer": "D",
      "explanation": "환경은 강화 학습에서 에이전트가 상호작용하는 외부 세계이자 보상과 상태를 제공하는 역할을 합니다."
    },
    {
      "id": 5,
      "objective_id": 2,
      "question": "강화 학습에서 '상태'란 무엇을 의미하나요?",
      "options": {
        "A": "에이전트의 위치",
        "B": "에이전트가 받는 보상의 총합",
        "C": "에이전트가 관찰 가능한 환경의 모든 특성",
        "D": "에이전트가 취할 수 있는 행동"
      },
      "answer": "C",
      "explanation": "상태는 에이전트가 관찰 가능한 환경의 모든 특성을 의미합니다."
    },
    {
      "id": 6,
      "objective_id": 2,
      "question": "강화 학습에서 에이전트의 '행동'은 어떻게 결정되나요?",
      "options": {
        "A": "환경이 결정한다.",
        "B": "상태에 따라 에이전트의 정책에 의해 결정된다.",
        "C": "항상 무작위로 결정된다.",
        "D": "보상의 크기에 따라 결정된다."
      },
      "answer": "B",
      "explanation": "에이전트의 행동은 현재 상태에 따라 정책에 의해 결정됩니다."
    },
    {
      "id": 7,
      "objective_id": 2,
      "question": "강화 학습에서 에이전트, 환경, 상태, 행동, 보상 사이의 상호작용을 가장 잘 설명하는 것은 무엇인가요?",
      "options": {
        "A": "에이전트는 정책에 따라 행동을 선택하고, 행동은 환경에 영향을 미치며, 환경은 새로운 상태와 보상을 에이전트에게 제공한다.",
        "B": "에이전트는 보상을 최대화하기 위해 환경을 변경한다.",
        "C": "상태는 행동을 결정하고, 행동은 보상을 결정한다.",
        "D": "보상은 에이전트와 환경 사이의 모든 상호작용을 결정한다."
      },
      "answer": "A",
      "explanation": "에이전트는 정책에 따라 행동을 선택하고, 행동은 환경에 영향을 미친 후, 환경은 새로운 상태와 보상을 에이전트에게 제공합니다. 보상은 에이전트가 이전에 취한 행동을 평가하기 위해 사용되고, 상태는 다음 행동을 결정하는 데에 사용됩니다."
    },
    {
      "id": 8,
      "objective_id": 3,
      "question": "강화 학습에서 '정책'이란 무엇인가요?",
      "options": {
        "A": "에이전트가 취하는 모든 행동의 집합",
        "B": "에이전트가 어떤 상태에서 어떤 행동을 취할지 결정하는 규칙",
        "C": "에이전트가 받는 즉각적인 보상",
        "D": "에이전트의 학습 알고리즘"
      },
      "answer": "B",
      "explanation": "정책은 에이전트가 어떤 상태에서 어떤 행동을 취할지를 결정하는 규칙입니다."
    },
    {
      "id": 9,
      "objective_id": 3,
      "question": "강화 학습의 최적화 과정에서 정책의 역할이 중요한 이유는 무엇입니까?",
      "options": {
        "A": "정책이 에이전트에게 최적의 행동을 지시하기 때문이다.",
        "B": "정책이 환경을 제어하기 때문이다.",
        "C": "정책이 모든 상태를 방문하기 때문이다.",
        "D": "정책이 보상의 크기를 결정하기 때문이다."
      },
      "answer": "A",
      "explanation": "정책이 에이전트에게 최적의 행동을 지시하기 때문입니다."
    },
    {
      "id": 10,
      "objective_id": 3,
      "question": "강화학습에서 정책 최적화 과정을 설명하고, 이 과정에서 에이전트가 어떻게 행동의 가치를 학습하는지 서술하세요.",
      "options": {
        "A": "정책 최적화는 에이전트가 모든 행동을 시도하고 가장 낮은 보상을 받는 행동을 선택하는 과정이다.",
        "B": "정책 최적화는 에이전트가 가능한 모든 상태와 행동을 평가하고, 각 상태에서 가장 높은 보상을 제공하는 행동을 선택하는 과정이다.",
        "C": "정책 최적화는 에이전트가 환경을 변경하고 새로운 상태를 생성하는 과정이다.",
        "D": "정책 최적화는 에이전트가 행동을 무작위로 선택하고 결과를 기록하는 과정이다."
      },
      "answer": "B",
      "explanation": "정책 최적화는 에이전트가 가능한 모든 상태와 행동을 평가하고, 각 상태에서 가장 높은 보상을 제공하는 행동을 선택하는 과정입니다. 이 과정을 통해 에이전트는 행동의 가치를 학습하며, 이를 바탕으로 정책을 점차 최적화합니다."
    }
  ]
}
